{"Title":"Monsters","Year":"2010","Rated":"R","Released":"03 Dec 2010","Runtime":"94 min","Genre":"Adventure, Drama, Romance","Director":"Gareth Edwards","Writer":"Gareth Edwards","Actors":"Scoot McNairy, Whitney Able, Mario Zuniga Benavides","Plot":"Six years after Earth has suffered an alien invasion, a cynical journalist agrees to escort a shaken American tourist through an infected zone in Mexico to the safety of the U.S. border.","Language":"English, Spanish","Country":"United Kingdom, Mexico","Awards":"Nominated for 1 BAFTA Award14 wins & 15 nominations total","Poster":"https://m.media-amazon.com/images/M/MV5BMjE4MzMyNjExMl5BMl5BanBnXkFtZTcwMzI5NjM3Mw@@._V1_SX300.jpg","Ratings":[{"Source":"Internet Movie Database","Value":"6.4/10"},{"Source":"Rotten Tomatoes","Value":"73%"},{"Source":"Metacritic","Value":"63/100"}],"Metascore":"63","imdbRating":"6.4","imdbVotes":"93,699","imdbID":"tt1470827","Type":"movie","DVD":"01 Feb 2011","BoxOffice":"$237,301","Production":"N/A","Website":"N/A","Response":"True"}